pep723_to_wheel/__init__.py
pep723_to_wheel/cli.py
pep723_to_wheel/core.py
pep723_to_wheel-0.1.1.dist-info/METADATA
pep723_to_wheel-0.1.1.dist-info/WHEEL
pep723_to_wheel-0.1.1.dist-info/entry_points.txt
pep723_to_wheel-0.1.1.dist-info/licenses/LICENSE
pep723_to_wheel-0.1.1.dist-info/RECORD
