Metadata-Version: 2.4
Name: pep723-to-wheel
Version: 0.1.1
Summary: PoC for pep-723 script to wheel and back
Project-URL: Homepage, https://github.com/jooh/pep723-to-wheel
Project-URL: Repository, https://github.com/jooh/pep723-to-wheel
Project-URL: Issues, https://github.com/jooh/pep723-to-wheel/issues
License: MIT License
License-File: LICENSE
Classifier: License :: OSI Approved :: MIT License
Classifier: Operating System :: OS Independent
Classifier: Programming Language :: Python :: 3
Classifier: Programming Language :: Python :: 3.12
Requires-Python: >=3.12
Requires-Dist: pydantic>=2.5
Requires-Dist: tomli-w>=1.1.0
Requires-Dist: typer>=0.21.1
